Metadata-Version: 2.1
Name: odoo12-addon-base-report-to-printer
Version: 12.0.1.2.1
Summary: Report to printer
Home-page: http://www.agilebg.com
Author: Agile Business Group & Domsense, Pegueroles SCP, NaN, LasLabs, Camptocamp, Odoo Community Association (OCA), Open for Small Business Ltd
Author-email: support@odoo-community.org
License: AGPL-3
Platform: UNKNOWN
Classifier: Programming Language :: Python
Classifier: Framework :: Odoo
Classifier: Framework :: Odoo :: 12.0
Classifier: License :: OSI Approved :: GNU Affero General Public License v3
Requires-Python: >=3.5
Requires-Dist: odoo (<12.1dev,>=12.0a)
Requires-Dist: pycups
